hyray/__init__.py
hyray/curay.py
hyray-0.1.0.dist-info/LICENSE
hyray-0.1.0.dist-info/METADATA
hyray-0.1.0.dist-info/WHEEL
hyray-0.1.0.dist-info/top_level.txt
hyray-0.1.0.dist-info/RECORD
